django_lti_authentication-0.2.0.dist-info/licenses/LICENSE
lti_authentication/__init__.py
lti_authentication/backends.py
lti_authentication/middleware.py
lti_authentication/tests/__init__.py
lti_authentication/tests/settings.py
lti_authentication/tests/test_backends.py
lti_authentication/tests/test_middleware.py
django_lti_authentication-0.2.0.dist-info/METADATA
django_lti_authentication-0.2.0.dist-info/WHEEL
django_lti_authentication-0.2.0.dist-info/top_level.txt
django_lti_authentication-0.2.0.dist-info/RECORD
