Metadata-Version: 2.4
Name: django-lti-authentication
Version: 0.2.0
Summary: Add-on to django-lti to integrate with Django's authentication system.
Author-email: Harvard University Academic Technology <academictechnology@harvard.edu>
Project-URL: Homepage, https://github.com/Harvard-University-iCommons/django-lti-authentication
Classifier: Environment :: Web Environment
Classifier: Framework :: Django
Classifier: Framework :: Django :: 4.2
Classifier: Framework :: Django :: 5.0
Classifier: Framework :: Django :: 5.1
Classifier: Framework :: Django :: 5.2
Classifier: Intended Audience :: Developers
Classifier: License :: OSI Approved :: MIT License
Classifier: Operating System :: OS Independent
Classifier: Programming Language :: Python
Classifier: Programming Language :: Python :: 3
Classifier: Programming Language :: Python :: 3 :: Only
Classifier: Programming Language :: Python :: 3.10
Classifier: Programming Language :: Python :: 3.11
Classifier: Programming Language :: Python :: 3.12
Classifier: Programming Language :: Python :: 3.13
Classifier: Topic :: Internet :: WWW/HTTP
Classifier: Topic :: Internet :: WWW/HTTP :: Dynamic Content
Requires-Python: >=3.10
License-File: LICENSE
Requires-Dist: django<5.3,>=4.2
Requires-Dist: django-lti>=0.5.0
Provides-Extra: dev
Requires-Dist: pytest==8.3.5; extra == "dev"
Requires-Dist: pytest-django==4.10.0; extra == "dev"
Requires-Dist: pytest-cov==6.0.0; extra == "dev"
Requires-Dist: mock==5.2.0; extra == "dev"
Requires-Dist: isort==6.0.1; extra == "dev"
Requires-Dist: black==25.1.0; extra == "dev"
Requires-Dist: coverage==7.6.12; extra == "dev"
Requires-Dist: flake8==7.1.2; extra == "dev"
Requires-Dist: flake8-pyproject==1.2.3; extra == "dev"
Dynamic: license-file
